[
  {
    "id": 1,
    "nome": "Ana Souza",
    "email": "user0@mail.com"
  },
  {
    "id": 2,
    "nome": "Bruno Lima",
    "email": "user1@mail.com"
  },
  {
    "id": 3,
    "nome": "Carla Mota",
    "email": "user2@mail.com"
  },
  {
    "id": 4,
    "nome": "Diego Alves",
    "email": "user3@mail.com"
  },
  {
    "id": 5,
    "nome": "Elisa Prado",
    "email": "user4@mail.com"
  },
  {
    "id": 6,
    "nome": "Fabio Nunes",
    "email": "user5@mail.com"
  },
  {
    "id": 7,
    "nome": "Gilda Ramos",
    "email": "user6@mail.com"
  },
  {
    "id": 8,
    "nome": "Hugo Teles",
    "email": "user7@mail.com"
  },
  {
    "id": 9,
    "nome": "Iara Campos",
    "email": "user8@mail.com"
  },
  {
    "id": 10,
    "nome": "Jonas Dias",
    "email": "user9@mail.com"
  },
  {
    "id": 11,
    "nome": "Karen Melo",
    "email": "user10@mail.com"
  },
  {
    "id": 12,
    "nome": "Lucas Viana",
    "email": "user11@mail.com"
  },
  {
    "id": 13,
    "nome": "Ana Souza",
    "email": "user12@mail.com"
  },
  {
    "id": 14,
    "nome": "Bruno Lima",
    "email": "user13@mail.com"
  },
  {
    "id": 15,
    "nome": "Carla Mota",
    "email": "user14@mail.com"
  },
  {
    "id": 16,
    "nome": "Diego Alves",
    "email": "user15@mail.com"
  },
  {
    "id": 17,
    "nome": "Elisa Prado",
    "email": "user16@mail.com"
  },
  {
    "id": 18,
    "nome": "Fabio Nunes",
    "email": "user17@mail.com"
  },
  {
    "id": 19,
    "nome": "Gilda Ramos",
    "email": "user18@mail.com"
  },
  {
    "id": 20,
    "nome": "Hugo Teles",
    "email": "user19@mail.com"
  },
  {
    "id": 21,
    "nome": "Iara Campos",
    "email": "user20@mail.com"
  },
  {
    "id": 22,
    "nome": "Jonas Dias",
    "email": "user21@mail.com"
  },
  {
    "id": 23,
    "nome": "Karen Melo",
    "email": "user22@mail.com"
  },
  {
    "id": 24,
    "nome": "Lucas Viana",
    "email": "user23@mail.com"
  },
  {
    "id": 25,
    "nome": "Ana Souza",
    "email": "user24@mail.com"
  },
  {
    "id": 26,
    "nome": "Bruno Lima",
    "email": "user25@mail.com"
  },
  {
    "id": 27,
    "nome": "Carla Mota",
    "email": "user26@mail.com"
  },
  {
    "id": 28,
    "nome": "Diego Alves",
    "email": "user27@mail.com"
  },
  {
    "id": 29,
    "nome": "Elisa Prado",
    "email": "user28@mail.com"
  },
  {
    "id": 30,
    "nome": "Fabio Nunes",
    "email": "user29@mail.com"
  },
  {
    "id": 31,
    "nome": "Gilda Ramos",
    "email": "user30@mail.com"
  },
  {
    "id": 32,
    "nome": "Hugo Teles",
    "email": "user31@mail.com"
  },
  {
    "id": 33,
    "nome": "Iara Campos",
    "email": "user32@mail.com"
  },
  {
    "id": 34,
    "nome": "Jonas Dias",
    "email": "user33@mail.com"
  },
  {
    "id": 35,
    "nome": "Karen Melo",
    "email": "user34@mail.com"
  },
  {
    "id": 36,
    "nome": "Lucas Viana",
    "email": "user35@mail.com"
  },
  {
    "id": 37,
    "nome": "Ana Souza",
    "email": "user36@mail.com"
  },
  {
    "id": 38,
    "nome": "Bruno Lima",
    "email": "user37@mail.com"
  },
  {
    "id": 39,
    "nome": "Carla Mota",
    "email": "user38@mail.com"
  },
  {
    "id": 40,
    "nome": "Diego Alves",
    "email": "user39@mail.com"
  },
  {
    "id": 41,
    "nome": "Elisa Prado",
    "email": "user40@mail.com"
  },
  {
    "id": 42,
    "nome": "Fabio Nunes",
    "email": "user41@mail.com"
  },
  {
    "id": 43,
    "nome": "Gilda Ramos",
    "email": "user42@mail.com"
  },
  {
    "id": 44,
    "nome": "Hugo Teles",
    "email": "user43@mail.com"
  },
  {
    "id": 45,
    "nome": "Iara Campos",
    "email": null
  },
  {
    "id": 46,
    "nome": "Jonas Dias",
    "email": "user45@mail.com"
  },
  {
    "id": 47,
    "nome": "Karen Melo",
    "email": "user46@mail.com"
  },
  {
    "id": 48,
    "nome": "Lucas Viana",
    "email": "user47@mail.com"
  },
  {
    "id": 49,
    "nome": "Ana Souza",
    "email": "user48@mail.com"
  },
  {
    "id": 50,
    "nome": "Bruno Lima",
    "email": "user49@mail.com"
  },
  {
    "id": 51,
    "nome": "Carla Mota",
    "email": "user50@mail.com"
  },
  {
    "id": 52,
    "nome": "Diego Alves",
    "email": "user51@mail.com"
  },
  {
    "id": 53,
    "nome": "Elisa Prado",
    "email": "user52@mail.com"
  },
  {
    "id": 54,
    "nome": "Fabio Nunes",
    "email": "user53@mail.com"
  },
  {
    "id": 55,
    "nome": "Gilda Ramos",
    "email": "user54@mail.com"
  },
  {
    "id": 56,
    "nome": "Hugo Teles",
    "email": null
  },
  {
    "id": 57,
    "nome": "Iara Campos",
    "email": "user56@mail.com"
  },
  {
    "id": 58,
    "nome": "Jonas Dias",
    "email": null
  },
  {
    "id": 59,
    "nome": "Karen Melo",
    "email": "user58@mail.com"
  },
  {
    "id": 60,
    "nome": "Lucas Viana",
    "email": null
  },
  {
    "id": 61,
    "nome": "Ana Souza",
    "email": "user60@mail.com"
  },
  {
    "id": 62,
    "nome": "Bruno Lima",
    "email": "user61@mail.com"
  },
  {
    "id": 63,
    "nome": "Carla Mota",
    "email": null
  },
  {
    "id": 64,
    "nome": "Diego Alves",
    "email": "user63@mail.com"
  },
  {
    "id": 65,
    "nome": "Elisa Prado",
    "email": "user64@mail.com"
  },
  {
    "id": 66,
    "nome": "Fabio Nunes",
    "email": "user65@mail.com"
  },
  {
    "id": 67,
    "nome": "Gilda Ramos",
    "email": "user66@mail.com"
  },
  {
    "id": 68,
    "nome": "Hugo Teles",
    "email": "user67@mail.com"
  },
  {
    "id": 69,
    "nome": "Iara Campos",
    "email": "user68@mail.com"
  },
  {
    "id": 70,
    "nome": "Jonas Dias",
    "email": null
  },
  {
    "id": 71,
    "nome": "Karen Melo",
    "email": "user70@mail.com"
  },
  {
    "id": 72,
    "nome": "Lucas Viana",
    "email": "user71@mail.com"
  },
  {
    "id": 73,
    "nome": "Ana Souza",
    "email": "user72@mail.com"
  },
  {
    "id": 74,
    "nome": "Bruno Lima",
    "email": "user73@mail.com"
  },
  {
    "id": 75,
    "nome": "Carla Mota",
    "email": "user74@mail.com"
  },
  {
    "id": 76,
    "nome": "Diego Alves",
    "email": "user75@mail.com"
  },
  {
    "id": 77,
    "nome": "Elisa Prado",
    "email": "user76@mail.com"
  },
  {
    "id": 78,
    "nome": "Fabio Nunes",
    "email": null
  },
  {
    "id": 79,
    "nome": "Gilda Ramos",
    "email": "user78@mail.com"
  },
  {
    "id": 80,
    "nome": "Hugo Teles",
    "email": "user79@mail.com"
  },
  {
    "id": 81,
    "nome": "Iara Campos",
    "email": "user80@mail.com"
  },
  {
    "id": 82,
    "nome": "Jonas Dias",
    "email": "user81@mail.com"
  },
  {
    "id": 83,
    "nome": "Karen Melo",
    "email": "user82@mail.com"
  },
  {
    "id": 84,
    "nome": "Lucas Viana",
    "email": "user83@mail.com"
  },
  {
    "id": 85,
    "nome": "Ana Souza",
    "email": "user84@mail.com"
  },
  {
    "id": 86,
    "nome": "Bruno Lima",
    "email": "user85@mail.com"
  },
  {
    "id": 87,
    "nome": "Carla Mota",
    "email": "user86@mail.com"
  },
  {
    "id": 88,
    "nome": "Diego Alves",
    "email": "user87@mail.com"
  },
  {
    "id": 89,
    "nome": "Elisa Prado",
    "email": "user88@mail.com"
  },
  {
    "id": 90,
    "nome": "Fabio Nunes",
    "email": "user89@mail.com"
  },
  {
    "id": 91,
    "nome": "Gilda Ramos",
    "email": "user90@mail.com"
  },
  {
    "id": 92,
    "nome": "Hugo Teles",
    "email": "user91@mail.com"
  },
  {
    "id": 93,
    "nome": "Iara Campos",
    "email": null
  },
  {
    "id": 94,
    "nome": "Jonas Dias",
    "email": "user93@mail.com"
  },
  {
    "id": 95,
    "nome": "Karen Melo",
    "email": null
  },
  {
    "id": 96,
    "nome": "Lucas Viana",
    "email": "user95@mail.com"
  },
  {
    "id": 97,
    "nome": "Ana Souza",
    "email": "user96@mail.com"
  },
  {
    "id": 98,
    "nome": "Bruno Lima",
    "email": "user97@mail.com"
  },
  {
    "id": 99,
    "nome": "Carla Mota",
    "email": "user98@mail.com"
  },
  {
    "id": 100,
    "nome": "Diego Alves",
    "email": "user99@mail.com"
  },
  {
    "id": 101,
    "nome": "Elisa Prado",
    "email": "user100@mail.com"
  },
  {
    "id": 102,
    "nome": "Fabio Nunes",
    "email": null
  },
  {
    "id": 103,
    "nome": "Gilda Ramos",
    "email": "user102@mail.com"
  },
  {
    "id": 104,
    "nome": "Hugo Teles",
    "email": "user103@mail.com"
  },
  {
    "id": 105,
    "nome": "Iara Campos",
    "email": "user104@mail.com"
  },
  {
    "id": 106,
    "nome": "Jonas Dias",
    "email": "user105@mail.com"
  },
  {
    "id": 107,
    "nome": "Karen Melo",
    "email": "user106@mail.com"
  },
  {
    "id": 108,
    "nome": "Lucas Viana",
    "email": "user107@mail.com"
  },
  {
    "id": 109,
    "nome": "Ana Souza",
    "email": "user108@mail.com"
  },
  {
    "id": 110,
    "nome": "Bruno Lima",
    "email": "user109@mail.com"
  },
  {
    "id": 111,
    "nome": "Carla Mota",
    "email": "user110@mail.com"
  },
  {
    "id": 112,
    "nome": "Diego Alves",
    "email": "user111@mail.com"
  },
  {
    "id": 113,
    "nome": "Elisa Prado",
    "email": "user112@mail.com"
  },
  {
    "id": 114,
    "nome": "Fabio Nunes",
    "email": "user113@mail.com"
  },
  {
    "id": 115,
    "nome": "Gilda Ramos",
    "email": "user114@mail.com"
  },
  {
    "id": 116,
    "nome": "Hugo Teles",
    "email": "user115@mail.com"
  },
  {
    "id": 117,
    "nome": "Iara Campos",
    "email": "user116@mail.com"
  },
  {
    "id": 118,
    "nome": "Jonas Dias",
    "email": "user117@mail.com"
  },
  {
    "id": 119,
    "nome": "Karen Melo",
    "email": "user118@mail.com"
  },
  {
    "id": 120,
    "nome": "Lucas Viana",
    "email": "user119@mail.com"
  }
]
